alethiomics/__init__.py
alethiomics/de.py
alethiomics/plot.py
alethiomics/pykeen.py
alethiomics/stats.py
alethiomics/utils.py
alethiomics-0.2.6.dist-info/LICENSE
alethiomics-0.2.6.dist-info/METADATA
alethiomics-0.2.6.dist-info/WHEEL
alethiomics-0.2.6.dist-info/top_level.txt
alethiomics-0.2.6.dist-info/RECORD
